django_paddle_billing/__init__.py
django_paddle_billing/admin.py
django_paddle_billing/api.py
django_paddle_billing/apps.py
django_paddle_billing/encoders.py
django_paddle_billing/exceptions.py
django_paddle_billing/models.py
django_paddle_billing/settings.py
django_paddle_billing/signals.py
django_paddle_billing/tests.py
django_paddle_billing/urls.py
django_paddle_billing/utils.py
django_paddle_billing/views.py
django_paddle_billing/management/commands/sync_from_paddle.py
django_paddle_billing/migrations/0001_initial.py
django_paddle_billing/migrations/0002_alter_subscription_status.py
django_paddle_billing/migrations/0003_discount.py
django_paddle_billing/migrations/__init__.py
django_paddle_billing-0.1.14.dist-info/METADATA
django_paddle_billing-0.1.14.dist-info/WHEEL
django_paddle_billing-0.1.14.dist-info/licenses/LICENSE
django_paddle_billing-0.1.14.dist-info/RECORD
