Metadata-Version: 2.4
Name: django-paddle-billing
Version: 0.1.14
Summary: Django + Paddle Billing Integration
Project-URL: Documentation, https://github.com/websideproject/django-paddle-billing#readme
Project-URL: Issues, https://github.com/websideproject/django-paddle-billing/issues
Project-URL: Source, https://github.com/websideproject/django-paddle-billing
Author-email: Benjamin Gervan <benjamin@websideproject.com>
License-Expression: MIT
License-File: LICENSE
Classifier: Development Status :: 4 - Beta
Classifier: Programming Language :: Python
Classifier: Programming Language :: Python :: 3.9
Classifier: Programming Language :: Python :: 3.10
Classifier: Programming Language :: Python :: 3.11
Classifier: Programming Language :: Python :: Implementation :: CPython
Classifier: Programming Language :: Python :: Implementation :: PyPy
Requires-Python: >=3.9
Requires-Dist: django-json-widget
Requires-Dist: django>=4.2
Requires-Dist: paddle-billing-client>=0.2.15
Provides-Extra: all
Requires-Dist: djangorestframework; extra == 'all'
Requires-Dist: unfold; extra == 'all'
Provides-Extra: api
Requires-Dist: djangorestframework; extra == 'api'
Provides-Extra: unfold
Requires-Dist: unfold; extra == 'unfold'
